pdsando/__init__.py
pdsando/version.py
pdsando/core/__init__.py
pdsando/core/wrappers.py
pdsando/etl/__init__.py
pdsando/etl/constants.py
pdsando/etl/pandas/__init__.py
pdsando/etl/pandas/pipeline/__init__.py
pdsando/etl/pandas/pipeline/castcolumns.py
pdsando/etl/pandas/pipeline/conversions.py
pdsando/etl/pandas/pipeline/standardize.py
pdsando/etl/pandas/pipeline/scd/__init__.py
pdsando/etl/pandas/pipeline/scd/scd.py
pdsando/etl/pandas/pipeline/scd/templates.py
pdsando/etl/pyspark/__init__.py
pdsando/etl/pyspark/functions.py
pdsando/etl/pyspark/pipeline/__init__.py
pdsando/etl/pyspark/pipeline/scd.py
pdsando/etl/schema/__init__.py
pdsando/etl/schema/abstract.py
pdsando/etl/schema/arrow.py
pdsando/etl/schema/spark.py
pdsando/ta/__init__.py
pdsando/ta/datafeeds/__init__.py
pdsando/ta/datafeeds/polygon.py
pdsando/ta/datafeeds/tsdata.py
pdsando/ta/pipeline/__init__.py
pdsando/ta/pipeline/filters.py
pdsando/ta/pipeline/indicators.py
pdsando/ta/pipeline/strategies.py
pdsando/ta/pipeline/transforms.py
pdsando/ta/visualizations/__init__.py
pdsando/ta/visualizations/chart.py
pdsando-0.3.8.dist-info/LICENSE
pdsando-0.3.8.dist-info/METADATA
pdsando-0.3.8.dist-info/WHEEL
pdsando-0.3.8.dist-info/top_level.txt
pdsando-0.3.8.dist-info/RECORD
