Metadata-Version: 2.1
Name: pdsando
Version: 0.3.8
Summary: UNKNOWN
Home-page: https://github.com/natsunlee/pdsando
Author: Nathan Lee
Author-email: lee.nathan.sh@gmail.com
License: Apache 2.0
Platform: UNKNOWN
Requires-Dist: mplfinance
Requires-Dist: pdpipe
Requires-Dist: pandas
Requires-Dist: numpy
Requires-Dist: jsonschema
